django_cache_pydantic/__init__.py
django_cache_pydantic/apps.py
django_cache_pydantic/base.py
django_cache_pydantic/conf.py
django_cache_pydantic/defaults.py
django_cache_pydantic/manager.py
django_cache_pydantic/options.py
django_cache_pydantic/py.typed
django_cache_pydantic-0.1.1.dist-info/LICENSE
django_cache_pydantic-0.1.1.dist-info/METADATA
django_cache_pydantic-0.1.1.dist-info/WHEEL
django_cache_pydantic-0.1.1.dist-info/top_level.txt
django_cache_pydantic-0.1.1.dist-info/RECORD
